dlthub/__init__.py
dlthub/__plugin__.py
dlthub/current.py
dlthub/py.typed
dlthub/version.py
dlthub/_runner/__init__.py
dlthub/_runner/exceptions.py
dlthub/_runner/pipeline_runner.py
dlthub/_runner/plus_log_collector.py
dlthub/_runner/prefect_collector.py
dlthub/_runner/prefect_helpers.py
dlthub/_runner/trace_helpers.py
dlthub/_runner/trace_resource.py
dlthub/_runner/typing.py
dlthub/_runner/utils.py
dlthub/cache/__init__.py
dlthub/cache/cache.py
dlthub/cache/cli.py
dlthub/cache/config.py
dlthub/common/__init__.py
dlthub/common/cli.py
dlthub/common/constants.py
dlthub/common/exceptions.py
dlthub/common/configuration/__init__.py
dlthub/common/license/__init__.py
dlthub/common/license/cli.py
dlthub/common/license/decorators.py
dlthub/common/license/exceptions.py
dlthub/common/license/license.py
dlthub/data_quality/__init__.py
dlthub/data_quality/_check.py
dlthub/data_quality/_checks_runner.py
dlthub/data_quality/_dashboard.py
dlthub/data_quality/_serde.py
dlthub/data_quality/checks.py
dlthub/data_quality/storage.py
dlthub/dbt_generator/__init__.py
dlthub/dbt_generator/cli.py
dlthub/dbt_generator/config.py
dlthub/dbt_generator/exceptions.py
dlthub/dbt_generator/render.py
dlthub/dbt_generator/types.py
dlthub/dbt_generator/utils.py
dlthub/dbt_generator/templates/README.md.j2
dlthub/dbt_generator/templates/dbt_project.yml.j2
dlthub/dbt_generator/templates/main.py.j2
dlthub/dbt_generator/templates/requirements.txt.j2
dlthub/dbt_generator/templates/sources.yml.j2
dlthub/dbt_generator/templates/table_active_load_ids.sql.j2
dlthub/dbt_generator/templates/table_fact.sql.j2
dlthub/dbt_generator/templates/table_mart.sql.j2
dlthub/dbt_generator/templates/table_processed_load_ids.sql.j2
dlthub/dbt_generator/templates/table_staging.sql.j2
dlthub/destinations/__init__.py
dlthub/destinations/adapters.py
dlthub/destinations/dataset.py
dlthub/destinations/utils.py
dlthub/destinations/impl/__init__.py
dlthub/destinations/impl/filesystem/__init__.py
dlthub-0.20.1.dist-info/METADATA
dlthub-0.20.1.dist-info/WHEEL
dlthub-0.20.1.dist-info/entry_points.txt
dlthub-0.20.1.dist-info/licenses/LICENSE.md
dlthub-0.20.1.dist-info/RECORD
