Metadata-Version: 2.4
Name: dlthub
Version: 0.20.1
Summary: dlthub is a commercial extension to dlt
Author-email: "dltHub Inc." <services@dlthub.com>
Maintainer-email: Marcin Rudolf <marcin@dlthub.com>, Adrian Brudaru <adrian@dlthub.com>, Anton Burnashev <anton@dlthub.com>, David Scharf <david@dlthub.com>
License: # dltHub Software EULA
License-File: LICENSE.md
Keywords: etl
Classifier: Development Status :: 3 - Alpha
Classifier: Intended Audience :: Developers
Classifier: Operating System :: MacOS :: MacOS X
Classifier: Operating System :: Microsoft :: Windows
Classifier: Operating System :: POSIX :: Linux
Classifier: Programming Language :: Python :: 3.9
Classifier: Programming Language :: Python :: 3.10
Classifier: Programming Language :: Python :: 3.11
Classifier: Programming Language :: Python :: 3.12
Classifier: Programming Language :: Python :: 3.13
Classifier: Topic :: Software Development :: Libraries
Classifier: Typing :: Typed
Requires-Python: <3.15,>=3.9
Requires-Dist: python-jose>=3.5.0
Requires-Dist: ruamel-yaml>=0.18.10
Provides-Extra: cache
Requires-Dist: duckdb>0.9; extra == 'cache'
Provides-Extra: dbt
Requires-Dist: dbt-core<1.10; extra == 'dbt'
Requires-Dist: jinja2>=3.1.2; extra == 'dbt'
Requires-Dist: pydantic<2.12,>2; extra == 'dbt'
Provides-Extra: iceberg
Requires-Dist: boto3>=1.37.3; extra == 'iceberg'
Requires-Dist: duckdb>=1.3.2; extra == 'iceberg'
Requires-Dist: pyarrow>=17; extra == 'iceberg'
Requires-Dist: pyiceberg>=0.9.1; extra == 'iceberg'
Requires-Dist: sqlalchemy>2; extra == 'iceberg'
Provides-Extra: mcp
Requires-Dist: duckdb>=1.1.3; extra == 'mcp'
Requires-Dist: mcp>=1.2.1; extra == 'mcp'
Requires-Dist: pandas>=2.1.4; extra == 'mcp'
Requires-Dist: pyarrow>=17; extra == 'mcp'
Provides-Extra: mssql
Requires-Dist: pyodbc>=4.0.39; extra == 'mssql'
Requires-Dist: sqlalchemy>1.4; extra == 'mssql'
Provides-Extra: snowflake
Requires-Dist: dlt[snowflake]; extra == 'snowflake'
